{
  "Timestamp_reward": {
    "steps": [
      1,
      2,
      3,
      4,
      5,
      6,
      7,
      8,
      9,
      10,
      11,
      12,
      13,
      14,
      15,
      16,
      17,
      18,
      19,
      20,
      21,
      22,
      23,
      24,
      25,
      26,
      27,
      28,
      29,
      30,
      31,
      32,
      33,
      34,
      35,
      36,
      37,
      38,
      39,
      40,
      41,
      42,
      43,
      44,
      45,
      46,
      47,
      48,
      49,
      50,
      51,
      52,
      53,
      54,
      55,
      56,
      57,
      58,
      59,
      60,
      61
    ],
    "timestamps": [
      "2024-09-25T19:39:38.253370",
      "2024-09-25T19:39:39.271995",
      "2024-09-25T19:39:40.270329",
      "2024-09-25T19:39:41.568160",
      "2024-09-25T19:39:42.785901",
      "2024-09-25T19:39:43.784142",
      "2024-09-25T19:39:44.711682",
      "2024-09-25T19:39:45.614240",
      "2024-09-25T19:39:46.534412",
      "2024-09-25T19:39:47.419048",
      "2024-09-25T19:39:48.305073",
      "2024-09-25T19:39:49.200675",
      "2024-09-25T19:39:50.083315",
      "2024-09-25T19:39:50.990456",
      "2024-09-25T19:39:51.998759",
      "2024-09-25T19:39:52.981509",
      "2024-09-25T19:39:53.920991",
      "2024-09-25T19:39:54.921480",
      "2024-09-25T19:39:55.899859",
      "2024-09-25T19:39:56.895253",
      "2024-09-25T19:39:59.709593",
      "2024-09-25T19:40:00.608188",
      "2024-09-25T19:40:01.638223",
      "2024-09-25T19:40:02.611618",
      "2024-09-25T19:40:03.604087",
      "2024-09-25T19:40:04.552330",
      "2024-09-25T19:40:05.432974",
      "2024-09-25T19:40:06.389651",
      "2024-09-25T19:40:07.284289",
      "2024-09-25T19:40:08.189460",
      "2024-09-25T19:40:09.099060",
      "2024-09-25T19:40:10.014639",
      "2024-09-25T19:40:10.973211",
      "2024-09-25T19:40:12.016386",
      "2024-09-25T19:40:13.058341",
      "2024-09-25T19:40:13.914048",
      "2024-09-25T19:40:14.801338",
      "2024-09-25T19:40:15.655050",
      "2024-09-25T19:40:16.517741",
      "2024-09-25T19:40:17.426451",
      "2024-09-25T19:40:20.128309",
      "2024-09-25T19:40:21.038218",
      "2024-09-25T19:40:21.981134",
      "2024-09-25T19:40:22.913639",
      "2024-09-25T19:40:23.839468",
      "2024-09-25T19:40:24.757011",
      "2024-09-25T19:40:25.660255",
      "2024-09-25T19:40:26.593745",
      "2024-09-25T19:40:27.528206",
      "2024-09-25T19:40:28.501218",
      "2024-09-25T19:40:29.374880",
      "2024-09-25T19:40:30.266998",
      "2024-09-25T19:40:31.143654",
      "2024-09-25T19:40:32.058671",
      "2024-09-25T19:40:32.944588",
      "2024-09-25T19:40:33.815255",
      "2024-09-25T19:40:34.718079",
      "2024-09-25T19:40:35.644561",
      "2024-09-25T19:40:36.577414",
      "2024-09-25T19:40:37.473982",
      "2024-09-25T19:40:38.366634"
    ],
    "values": [
      -70.3,
      -72.2,
      -87.25,
      -84.0,
      -81.85,
      -84.2,
      -77.1,
      -76.45,
      -80.15,
      -81.75,
      -78.55,
      -76.7,
      -73.6,
      -87.0,
      -84.35,
      -81.4,
      -79.85,
      -76.7,
      -84.2,
      -85.05,
      -78.75,
      -73.2,
      -76.1,
      -87.75,
      -73.95,
      -86.3,
      -78.85,
      -84.2,
      -82.9,
      -70.65,
      -72.35,
      -78.3,
      -77.15,
      -84.9,
      -74.75,
      -78.4,
      -81.35,
      -85.6,
      -77.65,
      -72.15,
      -74.4,
      -78.65,
      -75.5,
      -83.05,
      -84.1,
      -78.3,
      -76.75,
      -80.25,
      -89.5,
      -84.75,
      -84.75,
      -76.05,
      -76.75,
      -76.8,
      -74.9,
      -81.3,
      -83.1,
      -87.85,
      -74.5,
      -71.1,
      -77.2
    ]
  },
  "episode_reward": {
    "steps": [
      {
        "dtype": "float32",
        "values": [
          -8015.0
        ]
      },
      {
        "dtype": "float32",
        "py/object": "numpy.ndarray",
        "values": [
          -7755.0
        ]
      },
      {
        "dtype": "float32",
        "py/object": "numpy.ndarray",
        "values": [
          -8025.0
        ]
      },
      {
        "dtype": "float32",
        "py/object": "numpy.ndarray",
        "values": [
          -7760.0
        ]
      },
      {
        "dtype": "float32",
        "py/object": "numpy.ndarray",
        "values": [
          -7705.0
        ]
      },
      {
        "dtype": "float32",
        "py/object": "numpy.ndarray",
        "values": [
          -7230.0
        ]
      },
      {
        "dtype": "float32",
        "py/object": "numpy.ndarray",
        "values": [
          -7680.0
        ]
      },
      {
        "dtype": "float32",
        "py/object": "numpy.ndarray",
        "values": [
          -8445.0
        ]
      },
      {
        "dtype": "float32",
        "py/object": "numpy.ndarray",
        "values": [
          -7470.0
        ]
      },
      {
        "dtype": "float32",
        "py/object": "numpy.ndarray",
        "values": [
          -7575.0
        ]
      }
    ],
    "timestamps": [
      "2024-09-25T19:40:41.509987",
      "2024-09-25T19:40:42.424539",
      "2024-09-25T19:40:43.500691",
      "2024-09-25T19:40:44.584790",
      "2024-09-25T19:40:45.595359",
      "2024-09-25T19:40:46.502661",
      "2024-09-25T19:40:47.446300",
      "2024-09-25T19:40:48.377549",
      "2024-09-25T19:40:49.371889",
      "2024-09-25T19:40:50.344612"
    ],
    "values": [
      1,
      2,
      3,
      4,
      5,
      6,
      7,
      8,
      9,
      10
    ]
  }
}